libpythonpro_fr0/__init__.py
libpythonpro_fr0/github_api.py
libpythonpro_fr0/spam/__init__.py
libpythonpro_fr0/spam/db.py
libpythonpro_fr0/spam/enviador_de_email.py
libpythonpro_fr0/spam/main.py
libpythonpro_fr0/spam/modelos.py
libpythonpro_fr0/tests/__init__.py
libpythonpro_fr0/tests/test_exemplo.py
libpythonpro_fr0/tests/test_spam/__init__.py
libpythonpro_fr0/tests/test_spam/conftest.py
libpythonpro_fr0/tests/test_spam/test_enviador_de_email.py
libpythonpro_fr0/tests/test_spam/test_envio_para_base_de_usuarios.py
libpythonpro_fr0/tests/test_spam/test_github_api.py
libpythonpro_fr0/tests/test_spam/test_usuarios.py
libpythonpro_fr0-0.1.dist-info/LICENSE
libpythonpro_fr0-0.1.dist-info/METADATA
libpythonpro_fr0-0.1.dist-info/WHEEL
libpythonpro_fr0-0.1.dist-info/top_level.txt
libpythonpro_fr0-0.1.dist-info/RECORD
